[{"first_name":"Jesus","last_name":"Giacobbo","email":"jgiacobbo0@patch.com","gender":"Male"},
{"first_name":"Katlin","last_name":"Keat","email":"kkeat1@home.pl","gender":"Polygender"},
{"first_name":"Lurline","last_name":"Brach","email":"lbrach2@ucsd.edu","gender":"Female"},
{"first_name":"Lemar","last_name":"Hue","email":"lhue3@xinhuanet.com","gender":"Male"},
{"first_name":"Helga","last_name":"Anglim","email":"hanglim4@hhs.gov","gender":"Female"},
{"first_name":"Bealle","last_name":"Luna","email":"bluna5@reverbnation.com","gender":"Male"},
{"first_name":"Mathe","last_name":"Dabnor","email":"mdabnor6@yolasite.com","gender":"Male"},
{"first_name":"Herrick","last_name":"Stairs","email":"hstairs7@booking.com","gender":"Male"},
{"first_name":"Oliviero","last_name":"Hindenburg","email":"ohindenburg8@cbsnews.com","gender":"Male"},
{"first_name":"Maryrose","last_name":"Leathem","email":"mleathem9@gizmodo.com","gender":"Female"},
{"first_name":"Ingeborg","last_name":"Melonby","email":"imelonbya@a8.net","gender":"Female"},
{"first_name":"Colleen","last_name":"Brumfield","email":"cbrumfieldb@ft.com","gender":"Genderqueer"},
{"first_name":"Arney","last_name":"Kinnear","email":"akinnearc@businessweek.com","gender":"Male"},
{"first_name":"Elvira","last_name":"Poter","email":"epoterd@phpbb.com","gender":"Female"},
{"first_name":"Nessa","last_name":"Haberfield","email":"nhaberfielde@istockphoto.com","gender":"Female"},
{"first_name":"Jordan","last_name":"Budnik","email":"jbudnikf@photobucket.com","gender":"Male"},
{"first_name":"Tarrance","last_name":"Key","email":"tkeyg@ezinearticles.com","gender":"Male"},
{"first_name":"Bobine","last_name":"Mossdale","email":"bmossdaleh@bigcartel.com","gender":"Female"},
{"first_name":"Staffard","last_name":"Craw","email":"scrawi@nymag.com","gender":"Male"},
{"first_name":"Bessy","last_name":"Nutley","email":"bnutleyj@newyorker.com","gender":"Female"},
{"first_name":"Ferdie","last_name":"Buffham","email":"fbuffhamk@linkedin.com","gender":"Male"},
{"first_name":"Carly","last_name":"Blick","email":"cblickl@ox.ac.uk","gender":"Female"},
{"first_name":"Arthur","last_name":"McCrorie","email":"amccroriem@adobe.com","gender":"Male"},
{"first_name":"Lesley","last_name":"Poulsum","email":"lpoulsumn@fc2.com","gender":"Male"},
{"first_name":"Adham","last_name":"Lace","email":"alaceo@time.com","gender":"Male"},
{"first_name":"Doralia","last_name":"Yanele","email":"dyanelep@telegraph.co.uk","gender":"Female"},
{"first_name":"Anny","last_name":"Bacchus","email":"abacchusq@state.gov","gender":"Female"},
{"first_name":"Walden","last_name":"Grew","email":"wgrewr@archive.org","gender":"Male"},
{"first_name":"Irv","last_name":"Ferreli","email":"iferrelis@latimes.com","gender":"Polygender"},
{"first_name":"Abdel","last_name":"Blomefield","email":"ablomefieldt@npr.org","gender":"Male"},
{"first_name":"Bryna","last_name":"Foley","email":"bfoleyu@oracle.com","gender":"Female"},
{"first_name":"Britt","last_name":"Lampel","email":"blampelv@istockphoto.com","gender":"Genderfluid"},
{"first_name":"Tyrone","last_name":"Yeldon","email":"tyeldonw@reddit.com","gender":"Male"},
{"first_name":"Elbertine","last_name":"Pavelin","email":"epavelinx@comsenz.com","gender":"Female"},
{"first_name":"Mignon","last_name":"Zarb","email":"mzarby@digg.com","gender":"Female"},
{"first_name":"Kira","last_name":"Janos","email":"kjanosz@fda.gov","gender":"Female"},
{"first_name":"Goober","last_name":"Luetkemeyers","email":"gluetkemeyers10@soundcloud.com","gender":"Male"},
{"first_name":"Guntar","last_name":"Siddeley","email":"gsiddeley11@mozilla.org","gender":"Male"},
{"first_name":"Ellerey","last_name":"Cheetham","email":"echeetham12@sina.com.cn","gender":"Male"},
{"first_name":"Klaus","last_name":"Mantram","email":"kmantram13@arstechnica.com","gender":"Male"},
{"first_name":"Clarance","last_name":"Bennoe","email":"cbennoe14@stanford.edu","gender":"Male"},
{"first_name":"Carol-jean","last_name":"Pentelow","email":"cpentelow15@csmonitor.com","gender":"Female"},
{"first_name":"Hermione","last_name":"Spurr","email":"hspurr16@joomla.org","gender":"Female"},
{"first_name":"Mallorie","last_name":"Shercliff","email":"mshercliff17@pagesperso-orange.fr","gender":"Female"},
{"first_name":"Kenneth","last_name":"Mold","email":"kmold18@bloomberg.com","gender":"Male"},
{"first_name":"Lily","last_name":"Brounfield","email":"lbrounfield19@army.mil","gender":"Female"},
{"first_name":"Asa","last_name":"Poschel","email":"aposchel1a@shop-pro.jp","gender":"Male"},
{"first_name":"Cassaundra","last_name":"Cashford","email":"ccashford1b@toplist.cz","gender":"Female"},
{"first_name":"Crin","last_name":"Goodbody","email":"cgoodbody1c@wikia.com","gender":"Female"},
{"first_name":"Joy","last_name":"Aylesbury","email":"jaylesbury1d@live.com","gender":"Female"},
{"first_name":"Desmund","last_name":"Grigolon","email":"dgrigolon1e@unesco.org","gender":"Male"},
{"first_name":"Cristionna","last_name":"Delwater","email":"cdelwater1f@aol.com","gender":"Female"},
{"first_name":"Hestia","last_name":"Curnnokk","email":"hcurnnokk1g@sphinn.com","gender":"Female"},
{"first_name":"Lian","last_name":"Sciacovelli","email":"lsciacovelli1h@youku.com","gender":"Female"},
{"first_name":"Tandie","last_name":"Ramble","email":"tramble1i@instagram.com","gender":"Female"},
{"first_name":"Miles","last_name":"Umbert","email":"mumbert1j@cyberchimps.com","gender":"Male"},
{"first_name":"Yevette","last_name":"Queree","email":"yqueree1k@miitbeian.gov.cn","gender":"Female"},
{"first_name":"Antonius","last_name":"Varvell","email":"avarvell1l@canalblog.com","gender":"Male"},
{"first_name":"Cesare","last_name":"Pasterfield","email":"cpasterfield1m@msn.com","gender":"Male"},
{"first_name":"Trstram","last_name":"Ricioppo","email":"tricioppo1n@chron.com","gender":"Polygender"},
{"first_name":"Ozzie","last_name":"Dean","email":"odean1o@amazon.com","gender":"Male"},
{"first_name":"Odele","last_name":"Gorcke","email":"ogorcke1p@ovh.net","gender":"Female"},
{"first_name":"Amos","last_name":"Queyeiro","email":"aqueyeiro1q@msu.edu","gender":"Male"},
{"first_name":"Barnett","last_name":"Crangle","email":"bcrangle1r@yahoo.com","gender":"Male"},
{"first_name":"Shawn","last_name":"Mingey","email":"smingey1s@ucoz.com","gender":"Male"},
{"first_name":"Constancy","last_name":"McLagan","email":"cmclagan1t@cbsnews.com","gender":"Genderfluid"},
{"first_name":"Crysta","last_name":"Basson","email":"cbasson1u@ovh.net","gender":"Female"},
{"first_name":"Worden","last_name":"Smitherham","email":"wsmitherham1v@topsy.com","gender":"Male"},
{"first_name":"Fiann","last_name":"Dwelly","email":"fdwelly1w@yale.edu","gender":"Female"},
{"first_name":"Michail","last_name":"Corrin","email":"mcorrin1x@exblog.jp","gender":"Male"},
{"first_name":"Harriott","last_name":"Spellard","email":"hspellard1y@flickr.com","gender":"Female"},
{"first_name":"Andrej","last_name":"Motto","email":"amotto1z@ameblo.jp","gender":"Male"},
{"first_name":"Malanie","last_name":"Foxley","email":"mfoxley20@stanford.edu","gender":"Female"},
{"first_name":"Ole","last_name":"Hedgeley","email":"ohedgeley21@vimeo.com","gender":"Male"},
{"first_name":"Trey","last_name":"Raoul","email":"traoul22@4shared.com","gender":"Male"},
{"first_name":"Richardo","last_name":"Caltera","email":"rcaltera23@wsj.com","gender":"Male"},
{"first_name":"Libbi","last_name":"Ketchen","email":"lketchen24@vkontakte.ru","gender":"Female"},
{"first_name":"Wernher","last_name":"Joisce","email":"wjoisce25@google.es","gender":"Male"},
{"first_name":"Fredericka","last_name":"Askham","email":"faskham26@theguardian.com","gender":"Female"},
{"first_name":"Moses","last_name":"Beal","email":"mbeal27@list-manage.com","gender":"Male"},
{"first_name":"Lona","last_name":"Dreger","email":"ldreger28@abc.net.au","gender":"Female"},
{"first_name":"Barnie","last_name":"Addy","email":"baddy29@blogger.com","gender":"Male"},
{"first_name":"Dewey","last_name":"Durtnall","email":"ddurtnall2a@salon.com","gender":"Polygender"},
{"first_name":"Waneta","last_name":"Vockins","email":"wvockins2b@tripod.com","gender":"Female"},
{"first_name":"Rossie","last_name":"Hunnawill","email":"rhunnawill2c@artisteer.com","gender":"Male"},
{"first_name":"Rafaelia","last_name":"Serot","email":"rserot2d@businessinsider.com","gender":"Female"},
{"first_name":"Lucina","last_name":"Auletta","email":"lauletta2e@google.nl","gender":"Agender"},
{"first_name":"Corly","last_name":"Brodhead","email":"cbrodhead2f@ask.com","gender":"Female"},
{"first_name":"Brenden","last_name":"Jephcote","email":"bjephcote2g@youku.com","gender":"Male"},
{"first_name":"Gustave","last_name":"Ambrogio","email":"gambrogio2h@japanpost.jp","gender":"Male"},
{"first_name":"Imelda","last_name":"Crusham","email":"icrusham2i@buzzfeed.com","gender":"Female"},
{"first_name":"Hedwig","last_name":"Middler","email":"hmiddler2j@theglobeandmail.com","gender":"Female"},
{"first_name":"Cass","last_name":"Aleksic","email":"caleksic2k@csmonitor.com","gender":"Bigender"},
{"first_name":"Charis","last_name":"Brosel","email":"cbrosel2l@desdev.cn","gender":"Female"},
{"first_name":"Loren","last_name":"Baudinelli","email":"lbaudinelli2m@microsoft.com","gender":"Male"},
{"first_name":"Seline","last_name":"Steere","email":"ssteere2n@nih.gov","gender":"Female"},
{"first_name":"Alvie","last_name":"Mickan","email":"amickan2o@springer.com","gender":"Male"},
{"first_name":"Alexis","last_name":"Copsey","email":"acopsey2p@163.com","gender":"Female"},
{"first_name":"Mallory","last_name":"Kelly","email":"mkelly2q@latimes.com","gender":"Male"},
{"first_name":"Luciano","last_name":"Klesse","email":"lklesse2r@smugmug.com","gender":"Male"}]